{
    "nctId": "NCT03995082",
    "briefTitle": "Breast Cancer Patient Engagement With Patient Reported Outcome Measure Survey",
    "officialTitle": "A Randomized Study of Breast Cancer Patient Engagement With Patient Reported Outcome Measure Survey Results",
    "overallStatus": "RECRUITING",
    "conditions": "Breast Cancer",
    "studyType": "INTERVENTIONAL",
    "phase": "NA",
    "allocation": "RANDOMIZED",
    "primaryPurpose": "HEALTH_SERVICES_RESEARCH",
    "enrollmentCount": 370,
    "primaryOutcomeMeasure": "BREAST Q patient satisfaction with breast surgeon domain",
    "eligibilityCriteria": "We will target all patients with a new diagnosis of breast cancer who present to the breast multi-disciplinary clinic.\n\nInclusion:\n\n* Adult (18 years of age or more)\n* Female\n* Patients with breast cancer\n* Patients who can independently complete surveys\n\nExclusion\n\n* Age \\<18 years\n* Male\n* Patients who cannot independently complete surveys",
    "sex": "FEMALE",
    "minimumAge": "N/A",
    "stdAges": "CHILD, ADULT, OLDER_ADULT"
}