{
    "nctId": "NCT04645849",
    "briefTitle": "Feasibility Study on the Characterization of the Immune Profile of Young Patients After Treatment for Breast Cancer",
    "officialTitle": "Feasibility Study on the Characterization of the Immune Profile of Young Patients After Treatment for Breast Cancer",
    "overallStatus": "UNKNOWN",
    "conditions": "Breast Cancer",
    "studyType": "OBSERVATIONAL",
    "phase": "N/A",
    "allocation": "N/A",
    "primaryPurpose": "N/A",
    "enrollmentCount": 26,
    "primaryOutcomeMeasure": "Identification of the relevant biological parameters of the innate / adaptive immune system",
    "eligibilityCriteria": "Inclusion Criteria:\n\n* Women with Breast cancer at initial diagnosis OR at the end of treatment\n* Chemotherapy planned or performed in the treatment plan\n* Patient not opposed to participate to the present study\n* Affiliated to a French social security scheme.\n\nExclusion Criteria:\n\n* metastatic breast cancer\n* pregnant or breastfeeding woman\n* Treatment with monoclonal antibodies or immunotherapy\n* Immunosuppressive therapy\n* Thymus irradiation\n* Chronic infection in progress\n* Inborn or acquired disease (other than breast cancer) impacting the immune system (SAA, Lupus...)\n* Subject under guardianship or deprived of liberty",
    "sex": "FEMALE",
    "minimumAge": "18 Years",
    "stdAges": "ADULT"
}