{
    "nctId": "NCT05301998",
    "briefTitle": "Tridimensional Geometric Modeling of the Breast",
    "officialTitle": "Tridimensional Geometric Modeling of the Breast. Interest in Creating a Generic Biomechanical Model Useful for Simulation and Surgical Prediction",
    "overallStatus": "COMPLETED",
    "conditions": "Breast Cancer, Skin Elasticity",
    "studyType": "INTERVENTIONAL",
    "phase": "NA",
    "allocation": "NA",
    "primaryPurpose": "OTHER",
    "enrollmentCount": 200,
    "primaryOutcomeMeasure": "Measurement of skin elasticity using a cutometer",
    "eligibilityCriteria": "Inclusion Criteria:\n\n* Female\n* Up to 18 years old\n* Understanding and acceptance of the protocol\n\nExclusion Criteria:\n\n* Person protected by law under guardianship or curatorship\n* Failure to obtain free, informed and written consent after a reflection period\n* A patient who is not a member or beneficiary of a national health insurance system\n* Patient with a skin disease or a skin lesion\n* Person deprived of liberty by judicial or administrative decision\n* Application of a cream on the skin within 12 hours before the measurements",
    "sex": "FEMALE",
    "minimumAge": "18 Years",
    "stdAges": "ADULT, OLDER_ADULT"
}