{
    "nctId": "NCT05620329",
    "briefTitle": "UNC Pleural Fluid Registry",
    "officialTitle": "University of North Carolina Pleural Fluid Registry",
    "overallStatus": "RECRUITING",
    "conditions": "Lung Cancer, Lung Infection, Breast Cancer, Malignant Pleural Effusion, Empyema",
    "studyType": "OBSERVATIONAL",
    "phase": "N/A",
    "allocation": "N/A",
    "primaryPurpose": "N/A",
    "enrollmentCount": 9999,
    "primaryOutcomeMeasure": "Creation of a pleural fluid registry",
    "eligibilityCriteria": "Inclusion Criteria:\n\n* Patients who are 18 years or older\n* Inpatients and outpatients\n* Diagnosed with pleural fluid, are referred for and undergo clinically indicated drainage who have clinical evidence of:\n* pulmonary infection (such as fever, leukocytosis, new or worsening infiltrate on chest x-ray, or clinical deterioration) with effusion\n* malignancy\n\nExclusion Criteria:\n\n* A subject will not be eligible for inclusion in this registry if, in the investigator's (or treating clinician's) opinion, the patient has any concurrent medical condition that may preclude their ability to undergo pleural fluid drainage safely.\n* Incarcerated individuals",
    "sex": "ALL",
    "minimumAge": "18 Years",
    "stdAges": "ADULT, OLDER_ADULT"
}